Workbook
Name Beg_Bal: #REF!
Name dep: 'FINAL REPORT'!$A$183:$C$232
Name drscrs: 'FINAL REPORT'!$A$149:$C$178
Name ELIGIBILITY_FOR_BANK_OVERDRAFT: #REF!
Name End_Bal: '[1]Loan Calculator'!$I$18:$I$377
Name Extra_Pay: #REF!
Name Header_Row: ROW('[1]Loan Calculator'!$A$17:$IV$17)
Name Int: #REF!
Name Interest_Rate: '[1]Loan Calculator'!$D$5
Name Last_Row: IF(Values_Entered,Header_Row+Number_of_Payments,Header_Row)
Name Loan_Amount: '[1]Loan Calculator'!$D$4
Name Loan_Start: '[1]Loan Calculator'!$D$7
Name Loan_Years: '[1]Loan Calculator'!$D$6
Name ns: 'FINAL REPORT'!$A$59:$C$101
Name Number_of_Payments: MATCH(0.01,End_Bal,-1)+1
Name Pay_Num: #REF!
Name pl: #REF!
Name Princ: #REF!
Name profitloss: 'FINAL REPORT'!$A$27:$C$54
Name RMCONS: #REF!
Name Sched_Pay: #REF!
Name Scheduled_Extra_Payments: #REF!
Name Scheduled_Monthly_Payment: #REF!
Name Total_Pay: #REF!
Name Values_Entered: IF(Loan_Amount*Interest_Rate*Loan_Years*Loan_Start>0,1,0)
Name wc: 'FINAL REPORT'!$A$4:$C$17

Sheet INFO PAGE
A2: PROJECT REPORT DETAILS
A5: 1) | B5: Full Name | C5: : | D5: MRS.TANUJA SINGH
A8: 2) | B8: Nature of Business | C8: : | D8: WORKS & LABOUR CONTRACTORS
A11: 3) | B11: Name Of Business | C11: : | D11: M/S SHREE ENTERPRISES
A13: 4) | B13: Address Of Business | C13: : | D13: BLDG NO.2, A WING, BLOCK NO 20,
D14: VISHRAM TOWER, SHREE NAGA
D15: THANE - 400604
D16: MAHARASHTRA
A19: 5) | B19: Nature of facilities required | C19: : | D19: TERM LOAN OF RS. 35 LACS
A21: 6) | B21: Primary Security | C21: : | D21: RESIDENTIAL PREMISES AT ASHAR AXIS,THANE

Sheet FRONT PAGE

Sheet FINAL REPORT
A2: M/S PHARMACY EXPRESS
A4: ELIGIBILITY FOR BANK CC
A6: Particulars | B6: 31 Mar,23 | C6: 31 Mar,24 | D6: 31 Mar,25 | E6: 31 Mar,26 | F6: 31 Mar,27
B7: PROVISIONAL | C7: PROJECTED | D7: PROJECTED | E7: PROJECTED | F7: PROJECTED
A8: Stock | B8: 24713.98 | C8: =C33 -> 0 | D8: 10893912 | E8: 9020159.5 | F8: 9541324.3
A9: Debtors | B9: 0 | C9: 9689299 | D9: 10744681 | E9: 10983452 | F9: 10063750
A10: Gross Working Capital | B10: =SUM(B8:B9) -> 24713.98 | C10: 21964689 | D10: 21638593 | E10: 20003611 | F10: 19605074
A11: Less: Creditors & O/s exp. | B11: 74132.14 | C11: 4229181.2 | D11: 2536938.5 | E11: 2917479.3 | F11: 3459787.2
A12: Net Working Capital | B12: =B10-B11 -> -49418.16 | C12: 17735508 | D12: 19101655 | E12: 17086132 | F12: 16145287
A13: Less: Margin @ 25% | B13: =B12*25% -> -12354.54 | C13: 4433877 | D13: 4775413.7 | E13: 4271532.9 | F13: 4036321.8
A14: Eligibility For CC (As per Working Capital Basis) | B14: 0 | C14: 13301631 | D14: 14326241 | E14: 12814599 | F14: 12108965
A15: Eligibility For CC (As per Sales Basis) | B15: 0 | C15: 11583813 | D15: 8715130 | E15: 10022399 | F15: 11225087
A16: CC Applied For | B16: 0 | C16: 2000000 | D16: 2000000 | E16: 2000000 | F16: 2000000
A17: Interest @ 12.00% * | B17: 0 | C17: =C16*12/100*1/12 -> 20000 | D17: =D16*12% -> 240000 | E17: =E16*12% -> 240000 | F17: =F16*12% -> 240000
A18: Factor applied for actual debit of interest to CC account | B18: 1 | C18: 1 | D18: 1 | E18: 1 | F18: 1
A24: ='INFO PAGE'!D11 -> M/S SHREE ENTERPRISES
A27: PROJECTED PROFIT & LOSS ACCOUNT
A29: Particulars | B29: 31 Mar,26 | C29: 31 Mar,27 | D29: 31 Mar,28 | E29: 31 Mar,29 | F29: 32 Mar,30 | G29: 32 Mar,31 | H29: 33 Mar,32 | I29: 33 Mar,33 | J29: 34 Mar,34 | K29: 34 Mar,35 | L29: 34 Mar,36
B30: PROVISIONAL | C30: PROJECTED | D30: PROJECTED | E30: PROJECTED | F30: PROJECTED | G30: PROJECTED | H30: PROJECTED | I30: PROJECTED | J30: PROJECTED | K30: PROJECTED | L30: PROJECTED
A32: Sale of Works Contract Service (i) | B32: 74644510 | C32: =B32*1.1 -> 82108961 | D32: =C32*1.08 -> 88677678 | E32: =D32*1.08 -> 95771892 | F32: =E32*1.13 -> 1.0822224e+08 | G32: =F32*1.15 -> 1.2445557e+08 | H32: =G32*1.11 -> 1.3814569e+08 | I32: =H32*1.12 -> 1.5472317e+08 | J32: =I32*1.13 -> 1.7483718e+08 | K32: =J32*1.1 -> 1.923209e+08 | L32: =K32*1.1 -> 2.1155299e+08
A33: Add: Closing Stock as at 31st March | B33: 0 | C33: 0 | D33: =C33*1.1 -> 0 | E33: =D33*1.1 -> 0 | F33: =E33*1.1 -> 0 | G33: =F33*1.1 -> 0 | H33: =G33*1.1 -> 0 | I33: =H33*1.1 -> 0 | J33: =I33*1.1 -> 0 | K33: =J33*1.1 -> 0 | L33: =K33*1.1 -> 0
A34: (A) | B34: =SUM(B32:B33) -> 74644510 | C34: =SUM(C32:C33) -> 82108961 | D34: =SUM(D32:D33) -> 88677678 | E34: =SUM(E32:E33) -> 95771892 | F34: =SUM(F32:F33) -> 1.0822224e+08 | G34: =SUM(G32:G33) -> 1.2445557e+08 | H34: =SUM(H32:H33) -> 1.3814569e+08 | I34: =SUM(I32:I33) -> 1.5472317e+08 | ... L34: =SUM(L32:L33) -> 2.1155299e+08
A36: Less: Purchases of Goods | B36: =58872474-1522664 -> 57349810 | C36: =C32*76% -> 62402810 | D36: =D32*76.5% -> 67838424 | E36: =E32*76.5% -> 73265497 | F36: =F32*77% -> 83331123 | G36: =G32*77% -> 95830792 | H36: =H32*76.7% -> 1.0595774e+08 | I36: =I32*76.7% -> 1.1867267e+08 | J36: =J32*76.7% -> 1.3410012e+08 | K36: =K32*76.7% -> 1.4751013e+08 | L36: =L32*76.7% -> 1.6226114e+08
A37: Labour Charges & Salary | B37: =1522664+10942979 -> 12465643 | C37: =C34*17% -> 13958523 | D37: =D34*16.7% -> 14809172 | E37: =E34*17% -> 16281222 | F37: =F34*16.8% -> 18181336 | G37: =G34*17% -> 21157448 | H37: =H34*17% -> 23484767 | I37: =I34*16.8% -> 25993492 | J37: =J34*16.9% -> 29547484 | K37: =K34*16.7% -> 32117590 | L37: =L34*16.8% -> 35540902
A38: (B) | B38: =SUM(B36:B37) -> 69815453 | C38: =SUM(C36:C37) -> 76361334 | D38: =SUM(D36:D37) -> 82647596 | E38: =SUM(E36:E37) -> 89546719 | F38: =SUM(F36:F37) -> 1.0151246e+08 | G38: =SUM(G36:G37) -> 1.1698824e+08 | H38: =SUM(H36:H37) -> 1.2944251e+08 | I38: =SUM(I36:I37) -> 1.4466616e+08 | ... L38: =SUM(L36:L37) -> 1.9780205e+08
A40: Gross Profit C=(A-B) | B40: =B34-B38 -> 4829057 | C40: =C34-C38 -> 5747627.3 | D40: =D34-D38 -> 6030082.1 | E40: =E34-E38 -> 6225173 | F40: =F34-F38 -> 6709778.8 | G40: =G34-G38 -> 7467334.4 | H40: =H34-H38 -> 8703178.3 | I40: =I34-I38 -> 10057006 | ... L40: =L34-L38 -> 13750944
A41: % of Gross Profit C/i | B41: =B40/B34% -> 6.4694068 | C41: =C40/C34% -> 7 | D41: =D40/D34% -> 6.8 | E41: =E40/E34% -> 6.5 | F41: =F40/F34% -> 6.2 | G41: =G40/G34% -> 6 | H41: =H40/H34% -> 6.3 | I41: =I40/I34% -> 6.5 | ... L41: =L40/L34% -> 6.5
A43: Less: Operating Expenses
A44: Administration, Selling and Distribution Expenses (See Schedule 1) | B44: ='SCH 2'!B23 -> 2413055 | C44: ='SCH 2'!C23 -> 2770657.4 | D44: ='SCH 2'!D23 -> 3040457.7 | E44: ='SCH 2'!E23 -> 3336674.5 | F44: ='SCH 2'!F23 -> 3661905.4 | G44: ='SCH 2'!G23 -> 4273499.3 | H44: ='SCH 2'!H23 -> 4691050.3 | I44: ='SCH 2'!I23 -> 5149593.7 | ... L44: ='SCH 2'!L23 -> 6813605.9
A45: TOTAL OPERATING EXP. | D45: 1836636.9 | E45: 2007831.9 | F45: 2208615.1
A46: NET PROFIT BEFORE DEP and INT | B46: =B40-B44 -> 2416002 | C46: =C40-C44 -> 2976969.9 | D46: =D40-D44 -> 2989624.4 | E46: =E40-E44 -> 2888498.5 | F46: =F40-F44 -> 3047873.3 | G46: =G40-G44 -> 3193835.1 | H46: =H40-H44 -> 4012128 | I46: =I40-I44 -> 4907412.3 | ... L46: =L40-L44 -> 6937338.4
A47: Interest on CC & Term Loan | B47: 295608 | C47: =EMI!J23+OD!E11 -> 485423.67 | D47: =EMI!J35+OD!E12 -> 611762.23 | E47: =EMI!J47+OD!E13 -> 559424.31 | F47: =EMI!J59+OD!E14 -> 503048.1 | G47: =EMI!J82+OD!E15 -> 376395.81 | H47: =EMI!J94+OD!E16 -> 311792.79 | I47: =EMI!J106+OD!E17 -> 246584.94 | J47: =EMI!J118+OD!E18 -> 175526.09 | K47: =EMI!J130+OD!E19 -> 97474.012 | L47: =EMI!J124+OD!E20+EMI!J130 -> 90929.177
A48: NET PROFIT BEFORE DEP | B48: =B46-B47 -> 2120394 | C48: =C46-C47 -> 2491546.2 | D48: =D46-D47 -> 2377862.2 | E48: =E46-E47 -> 2329074.2 | F48: =F46-F47 -> 2544825.2 | G48: =G46-G47 -> 2817439.3 | H48: =H46-H47 -> 3700335.2 | I48: =I46-I47 -> 4660827.4 | ... L48: =L46-L47 -> 6846409.2
A49: Less: Depreciation | B49: =B226 -> 32524.2 | C49: =C226 -> 51395.57 | D49: =D226 -> 65061.234 | E49: =E226 -> 51567.674 | F49: =F226 -> 41720.804 | G49: =G226 -> 34319.051 | H49: =H226 -> 47464.109 | I49: =I226 -> 40111.831 | ... L49: =L226 -> 24794.162
A50: NET PROFIT BEFORE TAX | B50: =B48-B49 -> 2087869.8 | C50: =C48-C49 -> 2440150.6 | D50: =D48-D49 -> 2312801 | E50: =E48-E49 -> 2277506.5 | F50: =F48-F49 -> 2503104.4 | G50: =G48-G49 -> 2783120.3 | H50: =H48-H49 -> 3652871.1 | I50: =I48-I49 -> 4620715.5 | ... L50: =L48-L49 -> 6821615
A51: Less: Income Tax | B51: =(B50-2000000)*26%+208000 -> 230846.15 | C51: =(C50-2400000)*31.2%+312000 -> 324527 | D51: =(2400000-D50)*26%+208000 -> 230671.75 | E51: =(2400000-E50)*26%+208000 -> 239848.32 | F51: =(F50-2400000)*31.2%+312000 -> 344168.58 | G51: =(G50-2400000)*31.2%+312000 -> 431533.52 | H51: =(H50-2400000)*31.2%+312000 -> 702895.78 | I51: =(I50-2400000)*31.2%+312000 -> 1004863.2 | J51: =(J50-2400000)*31.2%+312000 -> 1225170.3 | K51: =(K50-2400000)*31.2%+312000 -> 1547667.5 | L51: =(L50-2400000)*31.2%+312000 -> 1691543.9
A52: NET PROFIT AFTER TAX | B52: =B50-B51 -> 1857023.7 | C52: =C50-C51 -> 2115623.6 | D52: =D50-D51 -> 2082129.2 | E52: =E50-E51 -> 2037658.2 | F52: =F50-F51 -> 2158935.8 | G52: =G50-G51 -> 2351586.7 | H52: =H50-H51 -> 2949975.3 | I52: =I50-I51 -> 3615852.3 | ... L52: =L50-L51 -> 5130071.1
A53: NP RATIO (BEFORE DEP AND INT) | B53: 4.1614389 | C53: 5.3309405 | D53: 7.6148791 | E53: 7.2541806 | F53: 6.9934304 | G53: 6.9934304 | H53: 6.9934304 | I53: 6.9934304 | J53: 6.9934304 | K53: 6.9934304 | L53: 6.9934304
A54: NP RATIO (AFTER DEP AND INT) | B54: 1.1477912 | C54: 1.764267 | D54: 2.6227991 | E54: 2.5155614 | F54: 2.8272073 | G54: 2.8272073 | H54: 2.8272073 | I54: 2.8272073 | J54: 2.8272073 | K54: 2.8272073 | L54: 2.8272073
A57: =A24 -> M/S SHREE ENTERPRISES
A59: PROJECTED BALANCE SHEET
A61: Particulars | B61: =B29 -> 31 Mar,26 | C61: =C29 -> 31 Mar,27 | D61: =D29 -> 31 Mar,28 | E61: =E29 -> 31 Mar,29 | F61: =F29 -> 32 Mar,30 | G61: =G29 -> 32 Mar,31 | H61: =H29 -> 33 Mar,32 | I61: =I29 -> 33 Mar,33 | ... L61: =L29 -> 34 Mar,36
B62: =B30 -> PROVISIONAL | C62: PROJECTED | D62: PROJECTED | E62: PROJECTED | F62: PROJECTED | G62: PROJECTED | H62: PROJECTED | I62: PROJECTED | J62: PROJECTED | K62: PROJECTED | L62: PROJECTED
A64: SOURCES OF FUNDS
A66: Capital Account (See Schedule 2) | B66: ='SCH 2 cap'!B17 -> 1991424.7 | C66: ='SCH 2 cap'!C17 -> 3049236.5 | D66: ='SCH 2 cap'!D17 -> 4090301.1 | E66: ='SCH 2 cap'!E17 -> 5109130.2 | F66: ='SCH 2 cap'!F17 -> 6188598.1 | G66: ='SCH 2 cap'!G17 -> 7364391.5 | H66: ='SCH 2 cap'!H17 -> 8544381.6 | I66: ='SCH 2 cap'!I17 -> 9990722.5 | ... L66: ='SCH 2 cap'!L17 -> 15608536
A67: Secured loans from bank
A68: Bank CC | B68: 0 | C68: 0 | D68: 0 | E68: 0 | F68: 0
A69: Bank Term Loan | B69: 3323350 | C69: =EMI!F35+OD!C12 -> 6643355.3 | D69: =EMI!F47+OD!C13 -> 6051749.5 | E69: =EMI!F59+OD!C14 -> 5413995.7 | F69: =EMI!F59+OD!C15 -> 5053245.7 | G69: =EMI!F71+OD!C16 -> 4336234.2 | H69: =EMI!F82+OD!C17 -> 2576053.8 | I69: =EMI!F94+OD!C18 -> 1965543.2 | J69: =EMI!F106+OD!C19 -> 1300395.9 | K69: =EMI!F118+OD!C20 -> 959061.05 | L69: =EMI!F130 -> 200263.36
A71: Unecured loans | B71: 0 | C71: 0 | D71: 0 | E71: 0 | F71: 0
A74: TOTAL SOURCES OF FUNDS | B74: =SUM(B66:B71) -> 5314774.7 | C74: =SUM(C66:C71) -> 9692591.8 | D74: =SUM(D66:D71) -> 10142051 | E74: =SUM(E66:E71) -> 10523126 | F74: =SUM(F66:F71) -> 11241844 | G74: =SUM(G66:G71) -> 11700626 | H74: =SUM(H66:H71) -> 11120435 | I74: =SUM(I66:I71) -> 11956266 | ... L74: =SUM(L66:L71) -> 15808799
A76: EMPLOYED AS UNDER
A78: Fixed assets (i) | B78: =B227 -> 184303.8 | C78: =C227 -> 397908.23 | D78: =D227 -> 332847 | E78: =E227 -> 281279.32 | F78: =F227 -> 239558.52 | G78: =G227 -> 205239.47 | H78: =H227 -> 283525.36 | I78: =I227 -> 243413.52 | ... L78: =L227 -> 155543.85
A80: Invetments (Long Term Asset) (ii) | B80: 139900 | C80: =B80+350000 -> 489900 | D80: =C80+400000 -> 889900 | E80: =D80+400000 -> 1289900 | F80: =E80+400000 -> 1689900 | G80: =F80+400000 -> 2089900 | H80: =G80+400000 -> 2489900 | I80: =H80+400000 -> 2889900 | J80: =I80+400000 -> 3289900 | K80: =J80+400000 -> 3689900 | L80: =K80+150000 -> 3839900
A82: Current assets
A83: Stock (Finished Goods) | B83: =B33 -> 0 | C83: =C33 -> 0 | D83: =D33 -> 0 | E83: =E33 -> 0 | F83: =F33 -> 0 | G83: =G33 -> 0 | H83: =H33 -> 0 | I83: =I33 -> 0 | ... L83: =L33 -> 0
A84: Debtors | B84: 22029164 | C84: =C32/12*2.5-3627916 -> 13478118 | D84: =D32/12*2.5-2563598 -> 15910918 | E84: =E32/12*2.5-1839089 -> 18113389 | F84: =F32/12*2.5-437408 -> 22108892 | G84: =G32/12*2.5+870089 -> 26798334 | H84: =H32/12*2.5 -> 28780351 | I84: =I32/12*2.5 -> 32233994 | J84: =J32/12*2.5 -> 36424413 | K84: =K32/12*2.5+1728013 -> 41794867 | L84: =L32/12*2.5 -> 44073539
A85: Cash & Bank | B85: =15500+1258527 -> 1274027 | C85: 937017 | D85: 946906 | E85: 1267817 | F85: 1099470 | G85: 479465 | H85: =914908-20126 -> 894782 | I85: 1837860 | J85: 2667859 | K85: 2506302 | L85: 2506302
A86: Other Current Assets | B86: =1617909+9724322+905750+39000 -> 12286981 | C86: =B86*0.9 -> 11058283 | D86: =C86*0.9 -> 9952454.6 | E86: =D86*0.9 -> 8957209.1 | F86: =E86*0.9 -> 8061488.2 | G86: =F86*0.9 -> 7255339.4 | H86: =G86*0.9 -> 6529805.5 | I86: =H86*0.9 -> 5876824.9 | J86: =I86*0.9 -> 5289142.4 | ... L86: =K86*0.9 -> 4284205.4
A87: Gross Current Asset - A | B87: =SUM(B83:B86) -> 35590172 | C87: =SUM(C83:C86) -> 25473417 | D87: =SUM(D83:D86) -> 26810279 | E87: =SUM(E83:E86) -> 28338415 | F87: =SUM(F83:F86) -> 31269850 | G87: =SUM(G83:G86) -> 34533138 | H87: =SUM(H83:H86) -> 36204939 | I87: =SUM(I83:I86) -> 39948679 | ... L87: =SUM(L83:L86) -> 50864047
A89: Current Liabilities
A90: Sundry Creditors | B90: 29664003 | C90: =C38/12*2.5 -> 15908611 | D90: =D38/12*2.5 -> 17218249 | E90: =E38/12*2.5 -> 18655566 | F90: =F38/12*2.5 -> 21148429 | G90: =G38/12*2.5 -> 24372550 | H90: =H38/12*2.5 -> 26967189 | I90: =I38/12*2.5 -> 30138784 | J90: =J38/12*2.5 -> 34093250 | K90: =K38/12*2.5 -> 37422442 | L90: =L38/12*2.5-3210891 -> 37997868
A91: Income Tax Payable | B91: 0 | C91: =C51 -> 324527 | D91: =D51*0.1 -> 23067.175 | E91: =E51*0.1 -> 23984.832 | F91: =F51*0.1 -> 34416.858 | G91: =G51*0.1 -> 43153.352 | H91: =H51*0.1 -> 70289.578 | I91: =I51*0.1 -> 100486.32 | J91: =J51*0.1 -> 122517.03 | K91: =K51*0.1 -> 154766.75 | L91: =L51*0.1 -> 169154.39
A92: Duties & Taxes | B92: 911598 | C92: =(C32-C36)*12%*1/12 -> 197061.51 | D92: =(D32-D36)*12%*1/12 -> 208392.54 | E92: =(E32-E36)*12%*1/12 -> 225063.95 | F92: =(F32-F36)*12%*1/12 -> 248911.15 | G92: =(G32-G36)*12%*1/12 -> 286247.82 | H92: =(H32-H36)*12%*1/12 -> 321879.45 | I92: =(I32-I36)*12%*1/12 -> 360504.98 | J92: =(J32-J36)*12%*1/12 -> 407370.63 | ... L92: =(L32-L36)*12%*1/12 -> 492918.47
A93: TDS Payable | B93: 24000 | C93: 238434.08 | D93: 441266.08 | E93: 481852.69 | F93: 525708 | G93: 425701 | H93: 498571 | I93: 525951 | J93: 325751 | K93: 390750 | L93: 390750
A94: Total current liabilities - B | B94: =SUM(B90:B93) -> 30599601 | C94: =SUM(C90:C93) -> 16668634 | D94: =SUM(D90:D93) -> 17890975 | E94: =SUM(E90:E93) -> 19386468 | F94: =SUM(F90:F93) -> 21957465 | G94: =SUM(G90:G93) -> 25127652 | H94: =SUM(H90:H93) -> 27857929 | I94: =SUM(I90:I93) -> 31125726 | ... L94: =SUM(L90:L93) -> 39050691
A96: Net Working Capital (A-B) (iii) | B96: =B87-B94 -> 4990571 | C96: =C87-C94 -> 8804783.7 | D96: =D87-D94 -> 8919303.9 | E96: =E87-E94 -> 8951946.7 | F96: =F87-F94 -> 9312384.8 | G96: =G87-G94 -> 9405485.9 | H96: =H87-H94 -> 8347009.6 | I96: =I87-I94 -> 8822952.2 | ... L96: =L87-L94 -> 11813356
A99: TOTAL APPLICATION OF FUNDS (i+ii+iii) | B99: =B78+B80+B96 -> 5314774.8 | C99: =C78+C80+C96 -> 9692591.9 | D99: =D78+D80+D96 -> 10142051 | E99: =E78+E80+E96 -> 10523126 | F99: =F78+F80+F96 -> 11241843 | G99: =G78+G80+G96 -> 11700625 | H99: =H78+H80+H96 -> 11120435 | I99: =I78+I80+I96 -> 11956266 | ... L99: =L78+L80+L96 -> 15808799
B101: -0.17768559 | C101: 0.21890605 | D101: 0.13823399 | E101: -0.15927828 | F101: -0.43229692
A104: =A24 -> M/S SHREE ENTERPRISES
A106: CALCULATION OF RATIOS:
A108: Particulars | B108: =B29 -> 31 Mar,26 | C108: =C29 -> 31 Mar,27 | D108: =D29 -> 31 Mar,28 | E108: =E29 -> 31 Mar,29 | F108: =F29 -> 32 Mar,30 | G108: =G29 -> 32 Mar,31 | H108: =H29 -> 33 Mar,32 | I108: =I29 -> 33 Mar,33 | ... L108: =L29 -> 34 Mar,36
B109: =B30 -> PROVISIONAL | C109: =C30 -> PROJECTED | D109: =D30 -> PROJECTED | E109: =E30 -> PROJECTED | F109: =F30 -> PROJECTED | G109: =G30 -> PROJECTED | H109: =H30 -> PROJECTED | I109: =I30 -> PROJECTED | ... L109: =L30 -> PROJECTED
A110: Current Ratio | B110: =B87/B94 -> 1.1630927 | C110: =C87/C94 -> 1.5282247 | D110: =D87/D94 -> 1.4985365 | E110: =E87/E94 -> 1.4617626 | F110: =F87/F94 -> 1.4241102 | G110: =G87/G94 -> 1.3743082 | H110: =H87/H94 -> 1.2996278 | I110: =I87/I94 -> 1.2834617 | ... L110: =L87/L94 -> 1.3025134
A112: Lockup Levels in months
A114: Debtors (in months) | B114: =B167 -> 3.5414523 | C114: =C167 -> 1.96979 | D114: =D167 -> 2.15309 | E114: =E167 -> 2.2695663 | F114: =F167 -> 2.4514989 | G114: =G167 -> 2.5838939 | H114: =H167 -> 2.5 | I114: =I167 -> 2.5 | ... L114: =L167 -> 2.5
A116: Finished Goods (in months) | B116: =B177 -> 0 | C116: =C177 -> 0 | D116: =D177 -> 0 | E116: =E177 -> 0 | F116: =F177 -> 0 | G116: =G177 -> 0 | H116: =H177 -> 0 | I116: =I177 -> 0 | ... L116: =L177 -> 0
A118: Creditors (in months) | B118: =B157 -> 6.206961 | C118: =C157 -> 3.0592105 | D118: =D157 -> 3.0457516 | E118: =E157 -> 3.0555556 | F118: =F157 -> 3.0454545 | G118: =G157 -> 3.0519481 | H118: =H157 -> 3.0541069 | I118: =I157 -> 3.047588 | ... L118: =L157 -> 2.810127
A120: Performance
A122: Turnover | B122: =B32 -> 74644510 | C122: =C32 -> 82108961 | D122: =D32 -> 88677678 | E122: =E32 -> 95771892 | F122: =F32 -> 1.0822224e+08 | G122: =G32 -> 1.2445557e+08 | H122: =H32 -> 1.3814569e+08 | I122: =I32 -> 1.5472317e+08 | ... L122: =L32 -> 2.1155299e+08
A124: Growth % | B124: NA | C124: =(C122-B122)/B122 -> 0.1 | D124: =(D122-C122)/C122 -> 0.08 | E124: =(E122-D122)/D122 -> 0.08 | F124: =(F122-E122)/E122 -> 0.13 | G124: =(G122-F122)/F122 -> 0.15 | H124: =(H122-G122)/G122 -> 0.11 | I124: =(I122-H122)/H122 -> 0.12 | J124: =(J122-I122)/I122 -> 0.13 | ... L124: =(L122-K122)/K122 -> 0.1
A126: Gross Profit Ratio | B126: =B40/B32*100 -> 6.4694068 | C126: =C40/C32*100 -> 7 | D126: =D40/D32*100 -> 6.8 | E126: =E40/E32*100 -> 6.5 | F126: =F40/F32*100 -> 6.2 | G126: =G40/G32*100 -> 6 | H126: =H40/H32*100 -> 6.3 | I126: =I40/I32*100 -> 6.5 | ... L126: =L40/L32*100 -> 6.5
A128: Operating Profit Ratio | B128: =B52/B32 -> 0.024878235 | C128: =C52/C32 -> 0.02576605 | D128: =D52/D32 -> 0.023479745 | E128: =E52/E32 -> 0.021276161 | F128: =F52/F32 -> 0.019949096 | G128: =G52/G32 -> 0.018894989 | H128: =H52/H32 -> 0.021354089 | I128: =I52/I32 -> 0.023369818 | ... L128: =L52/L32 -> 0.02424958
A130: Profit Before Tax | B130: =B50 -> 2087869.8 | C130: =C50 -> 2440150.6 | D130: =D50 -> 2312801 | E130: =E50 -> 2277506.5 | F130: =F50 -> 2503104.4 | G130: =G50 -> 2783120.3 | H130: =H50 -> 3652871.1 | I130: =I50 -> 4620715.5 | ... L130: =L50 -> 6821615
A132: Depreciation | B132: =B49 -> 32524.2 | C132: =C49 -> 51395.57 | D132: =D49 -> 65061.234 | E132: =E49 -> 51567.674 | F132: =F49 -> 41720.804 | G132: =G49 -> 34319.051 | H132: =H49 -> 47464.109 | I132: =I49 -> 40111.831 | ... L132: =L49 -> 24794.162
A134: Net Cash Accruals | B134: =SUM(B130:B132) -> 2120394 | C134: =SUM(C130:C132) -> 2491546.2 | D134: =SUM(D130:D132) -> 2377862.2 | E134: =SUM(E130:E132) -> 2329074.2 | F134: =SUM(F130:F132) -> 2544825.2 | G134: =SUM(G130:G132) -> 2817439.3 | H134: =SUM(H130:H132) -> 3700335.2 | I134: =SUM(I130:I132) -> 4660827.4 | ... L134: =SUM(L130:L132) -> 6846409.2
A136: Interest on Term Loan | B136: =B47 -> 295608 | C136: =C47 -> 485423.67 | D136: =D47 -> 611762.23 | E136: =E47 -> 559424.31 | F136: =F47 -> 503048.1 | G136: =G47 -> 376395.81 | H136: =H47 -> 311792.79 | I136: =I47 -> 246584.94 | ... L136: =L47 -> 90929.177
A138: Net Profit before tax and Interest | B138: =B50+B47 -> 2383477.8 | C138: =C50+C47 -> 2925574.3 | D138: =D50+D47 -> 2924563.2 | E138: =E50+E47 -> 2836930.8 | F138: =F50+F47 -> 3006152.5 | G138: =G50+G47 -> 3159516.1 | H138: =H50+H47 -> 3964663.9 | I138: =I50+I47 -> 4867300.5 | ... L138: =L50+L47 -> 6912544.2
A140: Net worth | B140: ='SCH 2 cap'!B17 -> 1991424.7 | C140: ='SCH 2 cap'!C17 -> 3049236.5 | D140: ='SCH 2 cap'!D17 -> 4090301.1 | E140: ='SCH 2 cap'!E17 -> 5109130.2 | F140: ='SCH 2 cap'!F17 -> 6188598.1 | G140: ='SCH 2 cap'!G17 -> 7364391.5 | H140: ='SCH 2 cap'!H17 -> 8544381.6 | I140: ='SCH 2 cap'!I17 -> 9990722.5 | ... K140: ='SCH 2 cap'!K17 -> 13556508 | L140: ='SCH 2 cap'!M17 -> 0
A141: Represented by :
A142: Capital | B142: =B140 -> 1991424.7 | C142: =C140 -> 3049236.5 | D142: =D140 -> 4090301.1 | E142: =E140 -> 5109130.2 | F142: =F140 -> 6188598.1 | G142: =G140 -> 7364391.5 | H142: =H140 -> 8544381.6 | I142: =I140 -> 9990722.5 | ... L142: =L140 -> 0
A146: =A24 -> M/S SHREE ENTERPRISES
A149: Calculation of Sundry Creditors
A151: Particulars | B151: =B108 -> 31 Mar,26 | C151: =C108 -> 31 Mar,27 | D151: =D108 -> 31 Mar,28 | E151: =E108 -> 31 Mar,29 | F151: =F108 -> 32 Mar,30 | G151: =G108 -> 32 Mar,31 | H151: =H108 -> 33 Mar,32 | I151: =I108 -> 33 Mar,33 | ... L151: =L108 -> 34 Mar,36
B152: =B109 -> PROVISIONAL | C152: =C109 -> PROJECTED | D152: =D109 -> PROJECTED | E152: =E109 -> PROJECTED | F152: =F109 -> PROJECTED | G152: =G109 -> PROJECTED | H152: =H109 -> PROJECTED | I152: =I109 -> PROJECTED | ... L152: =L109 -> PROJECTED
A154: Total Purchases | B154: =B36 -> 57349810 | C154: =C36 -> 62402810 | D154: =D36 -> 67838424 | E154: =E36 -> 73265497 | F154: =F36 -> 83331123 | G154: =G36 -> 95830792 | H154: =H36 -> 1.0595774e+08 | I154: =I36 -> 1.1867267e+08 | ... L154: =L36 -> 1.6226114e+08
A155: Average Monthly purchase | B155: =B154/12 -> 4779150.8 | C155: =C154/12 -> 5200234.2 | D155: =D154/12 -> 5653202 | E155: =E154/12 -> 6105458.1 | F155: =F154/12 -> 6944260.3 | G155: =G154/12 -> 7985899.3 | H155: =H154/12 -> 8829811.8 | I155: =I154/12 -> 9889389.2 | ... L155: =L154/12 -> 13521762
A156: Creditors | B156: =B90 -> 29664003 | C156: =C90 -> 15908611 | D156: =D90 -> 17218249 | E156: =E90 -> 18655566 | F156: =F90 -> 21148429 | G156: =G90 -> 24372550 | H156: =H90 -> 26967189 | I156: =I90 -> 30138784 | ... L156: =L90 -> 37997868
A157: Creditors as to Monthly purchases | B157: =B156/B155 -> 6.206961 | C157: =C156/C155 -> 3.0592105 | D157: =D156/D155 -> 3.0457516 | E157: =E156/E155 -> 3.0555556 | F157: =F156/F155 -> 3.0454545 | G157: =G156/G155 -> 3.0519481 | H157: =H156/H155 -> 3.0541069 | I157: =I156/I155 -> 3.047588 | ... L157: =L156/L155 -> 2.810127
A159: Calculation of Sundry Debtors
A161: Particulars | B161: =B151 -> 31 Mar,26 | C161: =C151 -> 31 Mar,27 | D161: =D151 -> 31 Mar,28 | E161: =E151 -> 31 Mar,29 | F161: =F151 -> 32 Mar,30 | G161: =G151 -> 32 Mar,31 | H161: =H151 -> 33 Mar,32 | I161: =I151 -> 33 Mar,33 | ... L161: =L151 -> 34 Mar,36
...

Sheet SCH 2 cap
A3: ='FINAL REPORT'!A24:C24 -> M/S SHREE ENTERPRISES
A5: SCHEDULE 2: CAPITAL ACCOUNT
A7: Particulars | B7: ='FINAL REPORT'!B29 -> 31 Mar,26 | C7: ='FINAL REPORT'!C29 -> 31 Mar,27 | D7: ='FINAL REPORT'!D29 -> 31 Mar,28 | E7: ='FINAL REPORT'!E29 -> 31 Mar,29 | F7: ='FINAL REPORT'!F29 -> 32 Mar,30 | G7: ='FINAL REPORT'!G29 -> 32 Mar,31 | H7: ='FINAL REPORT'!H29 -> 33 Mar,32 | I7: ='FINAL REPORT'!I29 -> 33 Mar,33 | ... L7: ='FINAL REPORT'!L29 -> 34 Mar,36
B8: ='FINAL REPORT'!B30 -> PROVISIONAL | C8: ='FINAL REPORT'!C30 -> PROJECTED | D8: ='FINAL REPORT'!D30 -> PROJECTED | E8: ='FINAL REPORT'!E30 -> PROJECTED | F8: ='FINAL REPORT'!F30 -> PROJECTED | G8: ='FINAL REPORT'!G30 -> PROJECTED | H8: ='FINAL REPORT'!H30 -> PROJECTED | I8: ='FINAL REPORT'!I30 -> PROJECTED | ... L8: ='FINAL REPORT'!L30 -> PROJECTED
A9: Opening Bal | B9: 925750 | C9: =B17 -> 1991424.7 | D9: =C17 -> 3049236.5 | E9: =D17 -> 4090301.1 | F9: =E17 -> 5109130.2 | G9: =F17 -> 6188598.1 | H9: =G17 -> 7364391.5 | I9: =H17 -> 8544381.6 | J9: =I17 -> 9990722.5 | ... L9: =K17 -> 13556508
A11: Add: Net Profit during the year | B11: ='FINAL REPORT'!B52 -> 1857023.7 | C11: ='FINAL REPORT'!C52 -> 2115623.6 | D11: ='FINAL REPORT'!D52 -> 2082129.2 | E11: ='FINAL REPORT'!E52 -> 2037658.2 | F11: ='FINAL REPORT'!F52 -> 2158935.8 | G11: ='FINAL REPORT'!G52 -> 2351586.7 | H11: ='FINAL REPORT'!H52 -> 2949975.3 | I11: ='FINAL REPORT'!I52 -> 3615852.3 | ... L11: ='FINAL REPORT'!L52 -> 5130071.1
A12: Add: Other Income | B12: 0 | C12: 0 | D12: 0 | E12: 0 | F12: 0
B13: =B9+B11 -> 2782773.7 | C13: =C9+C11 -> 4107048.3 | D13: =D9+D11 -> 5131365.7 | E13: =E9+E11 -> 6127959.2 | F13: =F9+F11 -> 7268066 | G13: =G9+G11 -> 8540184.8 | H13: =H9+H11 -> 10314367 | I13: =I9+I11 -> 12160234 | ... L13: =L9+L11 -> 18686579
A15: Less: Drawings | B15: 791349 | C15: =C11*0.5 -> 1057811.8 | D15: =D11*0.5 -> 1041064.6 | E15: =E11*0.5 -> 1018829.1 | F15: =F11*0.5 -> 1079467.9 | G15: =G11*0.5 -> 1175793.4 | H15: =H11*0.6 -> 1769985.2 | I15: =I11*0.6 -> 2169511.4 | J15: =J11*0.6 -> 2460994.6 | K15: =K11*0.6 -> 2887683.1 | L15: =L11*0.6 -> 3078042.7
A17: Closing Bal | B17: =B13-B15 -> 1991424.7 | C17: =C13-C15 -> 3049236.5 | D17: =D13-D15 -> 4090301.1 | E17: =E13-E15 -> 5109130.2 | F17: =F13-F15 -> 6188598.1 | G17: =G13-G15 -> 7364391.5 | H17: =H13-H15 -> 8544381.6 | I17: =I13-I15 -> 9990722.5 | ... L17: =L13-L15 -> 15608536

Sheet SCH 2
A2: ='FINAL REPORT'!A24:C24 -> M/S SHREE ENTERPRISES
A4: SCHEDULE 1: ADMINISTRATION, SELLING AND DISTRIBUTION EXPENSES
A6: Particulars | B6: ='FINAL REPORT'!B29 -> 31 Mar,26 | C6: ='FINAL REPORT'!C29 -> 31 Mar,27 | D6: ='FINAL REPORT'!D29 -> 31 Mar,28 | E6: ='FINAL REPORT'!E29 -> 31 Mar,29 | F6: ='FINAL REPORT'!F29 -> 32 Mar,30 | G6: ='FINAL REPORT'!G29 -> 32 Mar,31 | H6: ='FINAL REPORT'!H29 -> 33 Mar,32 | I6: ='FINAL REPORT'!I29 -> 33 Mar,33 | ... L6: ='FINAL REPORT'!L29 -> 34 Mar,36
B7: ='FINAL REPORT'!B30 -> PROVISIONAL | C7: ='FINAL REPORT'!C30 -> PROJECTED | D7: ='FINAL REPORT'!D30 -> PROJECTED | E7: ='FINAL REPORT'!E30 -> PROJECTED | F7: ='FINAL REPORT'!F30 -> PROJECTED | G7: ='FINAL REPORT'!G30 -> PROJECTED | H7: ='FINAL REPORT'!H30 -> PROJECTED | I7: ='FINAL REPORT'!I30 -> PROJECTED | ... L7: ='FINAL REPORT'!L30 -> PROJECTED
A9: Travelling & Conveyance | B9: 12903 | C9: =B9*1.1 -> 14193.3 | D9: =C9*1.1 -> 15612.63 | E9: =D9*1.1 -> 17173.893 | F9: =E9*1.1 -> 18891.282 | G9: =F9*1.125 -> 21252.693 | H9: =G9*1.1 -> 23377.962 | I9: =H9*1.1 -> 25715.758 | J9: =I9*1.1 -> 28287.334 | K9: =J9*1.1 -> 31116.067 | L9: =K9*1.1 -> 34227.674
A10: Transport Charges | B10: 74214 | C10: =B10*1.1 -> 81635.4 | D10: =C10*1.08 -> 88166.232 | E10: =D10*1.08 -> 95219.531 | F10: =E10*1.08 -> 102837.09 | G10: =F10*1.08 -> 111064.06 | H10: =G10*1.08 -> 119949.19 | I10: =H10*1.08 -> 129545.12 | J10: =I10*1.08 -> 139908.73 | K10: =J10*1.08 -> 151101.43 | L10: =K10*1.08 -> 163189.54
A11: Loading & Unloading Charges | B11: =64005+12500 -> 76505 | C11: =B11*1.15 -> 87980.75 | D11: =C11*1.08 -> 95019.21 | E11: =D11*1.08 -> 102620.75 | F11: =E11*1.08 -> 110830.41 | G11: =F11*1.08 -> 119696.84 | H11: =G11*1.08 -> 129272.59 | I11: =H11*1.08 -> 139614.39 | J11: =I11*1.08 -> 150783.54 | K11: =J11*1.08 -> 162846.23 | L11: =K11*1.08 -> 175873.93
A12: Lunch & Refreshment | B12: 25750 | C12: =B12*1.15 -> 29612.5 | D12: =C12*1.1 -> 32573.75 | E12: =D12*1.1 -> 35831.125 | F12: =E12*1.1 -> 39414.238 | G12: =F12*1.16 -> 45720.516 | H12: =G12*1.1 -> 50292.567 | I12: =H12*1.1 -> 55321.824 | J12: =I12*1.1 -> 60854.006 | K12: =J12*1.1 -> 66939.407 | L12: =K12*1.1 -> 73633.347
A13: Insurance | B13: 13707 | C13: =B13*1.15 -> 15763.05 | D13: =C13*1.08 -> 17024.094 | E13: =D13*1.08 -> 18386.022 | F13: =E13*1.08 -> 19856.903 | G13: =F13*1.08 -> 21445.456 | H13: =G13*1.08 -> 23161.092 | I13: =H13*1.08 -> 25013.979 | J13: =I13*1.08 -> 27015.098 | K13: =J13*1.08 -> 29176.305 | L13: =K13*1.08 -> 31510.41
A14: Petrol Expenses | B14: 17632 | C14: =B14*1.15 -> 20276.8 | D14: =C14*1.09 -> 22101.712 | E14: =D14*1.09 -> 24090.866 | F14: =E14*1.09 -> 26259.044 | G14: =F14*1.09 -> 28622.358 | H14: =G14*1.09 -> 31198.37 | I14: =H14*1.09 -> 34006.224 | J14: =I14*1.09 -> 37066.784 | K14: =J14*1.09 -> 40402.794 | L14: =K14*1.09 -> 44039.046
A15: Office Expenses | B15: 117083 | C15: =B15*1.15 -> 134645.45 | D15: =C15*1.08 -> 145417.09 | E15: =D15*1.08 -> 157050.45 | F15: =E15*1.08 -> 169614.49 | G15: =F15*1.08 -> 183183.65 | H15: =G15*1.08 -> 197838.34 | I15: =H15*1.08 -> 213665.41 | J15: =I15*1.08 -> 230758.64 | K15: =J15*1.08 -> 249219.33 | L15: =K15*1.08 -> 269156.88
A16: Telephone & Communication Exp. | B16: 3850 | C16: =B16*1.15 -> 4427.5 | D16: =C16*1.1 -> 4870.25 | E16: =D16*1.1 -> 5357.275 | F16: =E16*1.1 -> 5893.0025 | G16: =F16*1.18 -> 6953.743 | H16: =G16*1.1 -> 7649.1172 | I16: =H16*1.1 -> 8414.029 | J16: =I16*1.1 -> 9255.4319 | K16: =J16*1.1 -> 10180.975 | L16: =K16*1.1 -> 11199.073
A17: Professional Fees | B17: 19235 | C17: =B17*1.15 -> 22120.25 | D17: =C17*1.1 -> 24332.275 | E17: =D17*1.1 -> 26765.503 | F17: =E17*1.1 -> 29442.053 | G17: =F17*1.19 -> 35036.043 | H17: =G17*1.1 -> 38539.647 | I17: =H17*1.1 -> 42393.612 | J17: =I17*1.1 -> 46632.973 | K17: =J17*1.1 -> 51296.27 | L17: =K17*1.1 -> 56425.897
A18: Printing & Stationery | B18: 5000 | C18: =B18*1.15 -> 5750 | D18: =C18*1.1 -> 6325 | E18: =D18*1.1 -> 6957.5 | F18: =E18*1.1 -> 7653.25 | G18: =F18*1.18 -> 9030.835 | H18: =G18*1.1 -> 9933.9185 | I18: =H18*1.1 -> 10927.31 | J18: =I18*1.1 -> 12020.041 | K18: =J18*1.1 -> 13222.046 | L18: =K18*1.1 -> 14544.25
A19: Electricity Expenses | B19: 80485 | C19: =B19*1.15 -> 92557.75 | D19: =C19*1.1 -> 101813.53 | E19: =D19*1.1 -> 111994.88 | F19: =E19*1.1 -> 123194.37 | G19: =F19*1.17 -> 144137.41 | H19: =G19*1.1 -> 158551.15 | I19: =H19*1.1 -> 174406.26 | J19: =I19*1.1 -> 191846.89 | K19: =J19*1.1 -> 211031.58 | L19: =K19*1.1 -> 232134.74
A20: Repairs and Maintenance | B20: 2480 | C20: =B20*1.15 -> 2852 | D20: =C20*1.1 -> 3137.2 | E20: =D20*1.1 -> 3450.92 | F20: =E20*1.1 -> 3796.012 | G20: =F20*1.15 -> 4365.4138 | H20: =G20*1.1 -> 4801.9552 | I20: =H20*1.1 -> 5282.1507 | J20: =I20*1.1 -> 5810.3658 | K20: =J20*1.1 -> 6391.4023 | L20: =K20*1.1 -> 7030.5426
A21: Shop Rent | B21: 11517 | C21: =B21*1.15 -> 13244.55 | D21: =C21*1.05 -> 13906.778 | E21: =D21*1.05 -> 14602.116 | F21: =E21*1.05 -> 15332.222 | G21: =F21*1.05 -> 16098.833 | H21: =G21*1.05 -> 16903.775 | I21: =H21*1.05 -> 17748.964 | J21: =I21*1.05 -> 18636.412 | K21: =J21*1.05 -> 19568.232 | L21: =K21*1.05 -> 20546.644
A22: Misc Expenses | B22: 1952694 | C22: =B22*1.15 -> 2245598.1 | D22: =C22*1.1 -> 2470157.9 | E22: =D22*1.1 -> 2717173.7 | F22: =E22*1.1 -> 2988891.1 | G22: =F22*1.18 -> 3526891.5 | H22: =G22*1.1 -> 3879580.6 | I22: =H22*1.1 -> 4267538.7 | J22: =I22*1.1 -> 4694292.5 | K22: =J22*1.1 -> 5163721.8 | L22: =K22*1.1 -> 5680094
B23: =SUM(B9:B22) -> 2413055 | C23: =SUM(C9:C22) -> 2770657.4 | D23: =SUM(D9:D22) -> 3040457.7 | E23: =SUM(E9:E22) -> 3336674.5 | F23: =SUM(F9:F22) -> 3661905.4 | G23: =SUM(G9:G22) -> 4273499.3 | H23: =SUM(H9:H22) -> 4691050.3 | I23: =SUM(I9:I22) -> 5149593.7 | ... L23: =SUM(L9:L22) -> 6813605.9

Sheet EMI
B2: EMI CALCULATOR | I2: INSTRUCTION
B4: LOAN AMOUNT | D4: 4000000 | F4: FILL UP | I4: Please Fill Up Only Loan Amount, Rate Per Annum,and Nos. of Installments it will Automatically shows you the details of EMIs
B6: RATE OF INTEREST PER ANNUM | D6: 0.086 | F6: FILL UP
B8: RATE OF INTEREST PER MONTH | D8: =D6/12 -> 0.0071666667
B10: NO OF INSTALLMENT | D10: 120 | F10: FILL UP
D11: 62
B12: EMI | D12: =-PMT(D8,D10,D4) -> 49808.462
B14: CALCULATION OF DETAILS OF EMI
B16: MONTHS | C16: EMI | D16: INTEREST | E16: PRINCIPAL REPAYMENT | F16: OST PRINCIPAL | J16: Interest
B17: 0 | F17: =D4 -> 4000000
B18: 1 | C18: =D12 -> 49808.462 | D18: =F17*D8 -> 28666.667 | E18: =C18-D18 -> 21141.796 | F18: =F17-E18 -> 3978858.2
B19: 2 | C19: =D12 -> 49808.462 | D19: =F18*D8 -> 28515.15 | E19: =C19-D19 -> 21293.312 | F19: =F18-E19 -> 3957564.9
B20: 3 | C20: =D12 -> 49808.462 | D20: =F19*D8 -> 28362.548 | E20: =C20-D20 -> 21445.914 | F20: =F19-E20 -> 3936119
B21: 4 | C21: =D12 -> 49808.462 | D21: =F20*D8 -> 28208.853 | E21: =C21-D21 -> 21599.61 | F21: =F20-E21 -> 3914519.4
B22: 5 | C22: =D12 -> 49808.462 | D22: =F21*D8 -> 28054.055 | E22: =C22-D22 -> 21754.407 | F22: =F21-E22 -> 3892765
B23: 6 | C23: =D12 -> 49808.462 | D23: =F22*D8 -> 27898.149 | E23: =C23-D23 -> 21910.313 | F23: =F22-E23 -> 3870854.6 | J23: =SUM(D18:D23) -> 169705.42 | K23: 46447
B24: 7 | C24: =D12 -> 49808.462 | D24: =F23*D8 -> 27741.125 | E24: =C24-D24 -> 22067.337 | F24: =F23-E24 -> 3848787.3
B25: 8 | C25: =D12 -> 49808.462 | D25: =F24*D8 -> 27582.976 | E25: =C25-D25 -> 22225.487 | F25: =F24-E25 -> 3826561.8
B26: 9 | C26: =D12 -> 49808.462 | D26: =F25*D8 -> 27423.693 | E26: =C26-D26 -> 22384.769 | F26: =F25-E26 -> 3804177.1
B27: 10 | C27: =D12 -> 49808.462 | D27: =F26*D8 -> 27263.269 | E27: =C27-D27 -> 22545.193 | F27: =F26-E27 -> 3781631.9
B28: 11 | C28: =D12 -> 49808.462 | D28: =F27*D8 -> 27101.695 | E28: =C28-D28 -> 22706.767 | F28: =F27-E28 -> 3758925.1
B29: 12 | C29: =D12 -> 49808.462 | D29: =F28*D8 -> 26938.963 | E29: =C29-D29 -> 22869.499 | F29: =F28-E29 -> 3736055.6 | G29: 1 | I29: =SUM(D18:D29) -> 333757.14
B30: 13 | C30: =D12 -> 49808.462 | D30: =F29*D8 -> 26775.065 | E30: =C30-D30 -> 23033.397 | F30: =F29-E30 -> 3713022.2
B31: 14 | C31: =D12 -> 49808.462 | D31: =F30*D8 -> 26609.992 | E31: =C31-D31 -> 23198.47 | F31: =F30-E31 -> 3689823.7
B32: 15 | C32: =D12 -> 49808.462 | D32: =F31*D8 -> 26443.737 | E32: =C32-D32 -> 23364.726 | F32: =F31-E32 -> 3666459
B33: 16 | C33: =D12 -> 49808.462 | D33: =F32*D8 -> 26276.29 | E33: =C33-D33 -> 23532.173 | F33: =F32-E33 -> 3642926.8
B34: 17 | C34: =D12 -> 49808.462 | D34: =F33*D8 -> 26107.642 | E34: =C34-D34 -> 23700.82 | F34: =F33-E34 -> 3619226
B35: 18 | C35: =D12 -> 49808.462 | D35: =F34*D8 -> 25937.786 | E35: =C35-D35 -> 23870.676 | F35: =F34-E35 -> 3595355.3 | J35: =SUM(D24:D35) -> 322202.23 | K35: 46813
B36: 19 | C36: =D12 -> 49808.462 | D36: =F35*D8 -> 25766.713 | E36: =C36-D36 -> 24041.749 | F36: =F35-E36 -> 3571313.6
B37: 20 | C37: =D12 -> 49808.462 | D37: =F36*D8 -> 25594.414 | E37: =C37-D37 -> 24214.048 | F37: =F36-E37 -> 3547099.5
B38: 21 | C38: =D12 -> 49808.462 | D38: =F37*D8 -> 25420.88 | E38: =C38-D38 -> 24387.582 | F38: =F37-E38 -> 3522712
B39: 22 | C39: =D12 -> 49808.462 | D39: =F38*D8 -> 25246.102 | E39: =C39-D39 -> 24562.36 | F39: =F38-E39 -> 3498149.6
B40: 23 | C40: =D12 -> 49808.462 | D40: =F39*D8 -> 25070.072 | E40: =C40-D40 -> 24738.39 | F40: =F39-E40 -> 3473411.2
B41: 24 | C41: =D12 -> 49808.462 | D41: =F40*D8 -> 24892.78 | E41: =C41-D41 -> 24915.682 | F41: =F40-E41 -> 3448495.5 | G41: 2 | I41: =SUM(D30:D41) -> 310141.47
B42: 25 | C42: =D12 -> 49808.462 | D42: =F41*D8 -> 24714.218 | E42: =C42-D42 -> 25094.244 | F42: =F41-E42 -> 3423401.3
B43: 26 | C43: =D12 -> 49808.462 | D43: =F42*D8 -> 24534.376 | E43: =C43-D43 -> 25274.086 | F43: =F42-E43 -> 3398127.2
B44: 27 | C44: =D12 -> 49808.462 | D44: =F43*D8 -> 24353.245 | E44: =C44-D44 -> 25455.217 | F44: =F43-E44 -> 3372672
B45: 28 | C45: =D12 -> 49808.462 | D45: =F44*D8 -> 24170.816 | E45: =C45-D45 -> 25637.646 | F45: =F44-E45 -> 3347034.3
B46: 29 | C46: =D12 -> 49808.462 | D46: =F45*D8 -> 23987.079 | E46: =C46-D46 -> 25821.383 | F46: =F45-E46 -> 3321212.9
B47: 30 | C47: =D12 -> 49808.462 | D47: =F46*D8 -> 23802.026 | E47: =C47-D47 -> 26006.436 | F47: =F46-E47 -> 3295206.5 | J47: =SUM(D36:D47) -> 297552.72 | K47: 47178
B48: 31 | C48: =D12 -> 49808.462 | D48: =F47*D8 -> 23615.647 | E48: =C48-D48 -> 26192.816 | F48: =F47-E48 -> 3269013.7
B49: 32 | C49: =D12 -> 49808.462 | D49: =F48*D8 -> 23427.931 | E49: =C49-D49 -> 26380.531 | F49: =F48-E49 -> 3242633.2
B50: 33 | C50: =D12 -> 49808.462 | D50: =F49*D8 -> 23238.871 | E50: =C50-D50 -> 26569.591 | F50: =F49-E50 -> 3216063.6
B51: 34 | C51: =D12 -> 49808.462 | D51: =F50*D8 -> 23048.456 | E51: =C51-D51 -> 26760.007 | F51: =F50-E51 -> 3189303.6
B52: 35 | C52: =D12 -> 49808.462 | D52: =F51*D8 -> 22856.676 | E52: =C52-D52 -> 26951.787 | F52: =F51-E52 -> 3162351.8
B53: 36 | C53: =D12 -> 49808.462 | D53: =F52*D8 -> 22663.521 | E53: =C53-D53 -> 27144.941 | F53: =F52-E53 -> 3135206.8 | G53: 3 | I53: =SUM(D42:D53) -> 284412.86
B54: 37 | C54: =D12 -> 49808.462 | D54: =F53*D8 -> 22468.982 | E54: =C54-D54 -> 27339.48 | F54: =F53-E54 -> 3107867.4
B55: 38 | C55: =$D$12 -> 49808.462 | D55: =F54*D8 -> 22273.049 | E55: =C55-D55 -> 27535.413 | F55: =F54-E55 -> 3080331.9
B56: 39 | C56: =$D$12 -> 49808.462 | D56: =F55*D8 -> 22075.712 | E56: =C56-D56 -> 27732.75 | F56: =F55-E56 -> 3052599.2
B57: 40 | C57: =$D$12 -> 49808.462 | D57: =F56*D8 -> 21876.961 | E57: =C57-D57 -> 27931.501 | F57: =F56-E57 -> 3024667.7
B58: 41 | C58: =$D$12 -> 49808.462 | D58: =F57*D8 -> 21676.785 | E58: =C58-D58 -> 28131.677 | F58: =F57-E58 -> 2996536
B59: 42 | C59: =$D$12 -> 49808.462 | D59: =F58*D8 -> 21475.175 | E59: =C59-D59 -> 28333.288 | F59: =F58-E59 -> 2968202.7 | J59: =SUM(D48:D59) -> 270697.77 | K59: 11018
B60: 43 | C60: =$D$12 -> 49808.462 | D60: =F59*D8 -> 21272.12 | E60: =C60-D60 -> 28536.343 | F60: =F59-E60 -> 2939666.4
B61: 44 | C61: =$D$12 -> 49808.462 | D61: =F60*D8 -> 21067.609 | E61: =C61-D61 -> 28740.853 | F61: =F60-E61 -> 2910925.5
B62: 45 | C62: =$D$12 -> 49808.462 | D62: =F61*D8 -> 20861.633 | E62: =C62-D62 -> 28946.829 | F62: =F61-E62 -> 2881978.7
B63: 46 | C63: =$D$12 -> 49808.462 | D63: =F62*D8 -> 20654.181 | E63: =C63-D63 -> 29154.282 | F63: =F62-E63 -> 2852824.4
B64: 47 | C64: =$D$12 -> 49808.462 | D64: =F63*D8 -> 20445.242 | E64: =C64-D64 -> 29363.221 | F64: =F63-E64 -> 2823461.2
B65: 48 | C65: =$D$12 -> 49808.462 | D65: =F64*D8 -> 20234.805 | E65: =C65-D65 -> 29573.657 | F65: =F64-E65 -> 2793887.5 | G65: 4 | I65: =SUM(D54:D65) -> 256382.25
B66: 49 | C66: =$D$12 -> 49808.462 | D66: =F65*D8 -> 20022.861 | E66: =C66-D66 -> 29785.602 | F66: =F65-E66 -> 2764101.9
B67: 50 | C67: =$D$12 -> 49808.462 | D67: =F66*D8 -> 19809.397 | E67: =C67-D67 -> 29999.065 | F67: =F66-E67 -> 2734102.9
B68: 51 | C68: =$D$12 -> 49808.462 | D68: =F67*D8 -> 19594.404 | E68: =C68-D68 -> 30214.058 | F68: =F67-E68 -> 2703888.8
B69: 52 | C69: =$D$12 -> 49808.462 | D69: =F68*D8 -> 19377.87 | E69: =C69-D69 -> 30430.592 | F69: =F68-E69 -> 2673458.2
B70: 53 | C70: =$D$12 -> 49808.462 | D70: =F69*D8 -> 19159.784 | E70: =C70-D70 -> 30648.678 | F70: =F69-E70 -> 2642809.5
B71: 54 | C71: =$D$12 -> 49808.462 | D71: =F70*D8 -> 18940.135 | E71: =C71-D71 -> 30868.327 | F71: =F70-E71 -> 2611941.2 | J71: =SUM(D60:D71) -> 241440.04 | K71: 11383
B72: 55 | C72: =$D$12 -> 49808.462 | D72: =F71*D8 -> 18718.912 | E72: =C72-D72 -> 31089.55 | F72: =F71-E72 -> 2580851.7
B73: 56 | C73: =$D$12 -> 49808.462 | D73: =F72*D8 -> 18496.104 | E73: =C73-D73 -> 31312.359 | F73: =F72-E73 -> 2549539.3
B74: 57 | C74: =$D$12 -> 49808.462 | D74: =F73*D8 -> 18271.698 | E74: =C74-D74 -> 31536.764 | F74: =F73-E74 -> 2518002.5
B75: 58 | C75: =$D$12 -> 49808.462 | D75: =F74*D8 -> 18045.685 | E75: =C75-D75 -> 31762.777 | F75: =F74-E75 -> 2486239.8
B76: 59 | C76: =$D$12 -> 49808.462 | D76: =F75*D8 -> 17818.052 | E76: =C76-D76 -> 31990.411 | F76: =F75-E76 -> 2454249.4
B77: 60 | C77: =$D$12 -> 49808.462 | D77: =F76*D8 -> 17588.787 | E77: =C77-D77 -> 32219.675 | F77: =F76-E77 -> 2422029.7 | G77: 5 | I77: =SUM(D66:D77) -> 225843.69
B78: 62 | C78: 29862.134 | D78: 14218.143 | E78: 15643.991 | F78: 1296800
B79: 63 | C79: 29862.134 | D79: 14048.667 | E79: 15813.467 | F79: 1280986.5
B80: 64 | C80: 29862.134 | D80: 13877.354 | E80: 15984.78 | F80: 1265001.8
B81: 65 | C81: 29862.134 | D81: 13704.186 | E81: 16157.948 | F81: 1248843.8
B82: 66 | C82: 29862.134 | D82: 13529.141 | E82: 16332.993 | F82: 1232510.8 | J82: =SUM(D72:D82) -> 178316.73 | K82: 11749
B83: 67 | C83: 29862.134 | D83: 13352.201 | E83: 16509.934 | F83: 1216000.9
B84: 68 | C84: 29862.134 | D84: 13173.343 | E84: 16688.791 | F84: 1199312.1
B85: 69 | C85: 29862.134 | D85: 12992.548 | E85: 16869.586 | F85: 1182442.5
B86: 70 | C86: 29862.134 | D86: 12809.794 | E86: 17052.34 | F86: 1165390.2
B87: 71 | C87: 29862.134 | D87: 12625.06 | E87: 17237.074 | F87: 1148153.1
B88: 72 | C88: 29862.134 | D88: 12438.325 | E88: 17423.809 | F88: 1130729.3 | G88: 6 | I88: =SUM(D78:D88) -> 146768.76
B89: 73 | C89: 29862.134 | D89: 12249.567 | E89: 17612.567 | F89: 1113116.7
B90: 74 | C90: 29862.134 | D90: 12058.764 | E90: 17803.37 | F90: 1095313.3
B91: 75 | C91: 29862.134 | D91: 11865.895 | E91: 17996.24 | F91: 1077317.1
B92: 76 | C92: 29862.134 | D92: 11670.935 | E92: 18191.199 | F92: 1059125.9
B93: 77 | C93: 29862.134 | D93: 11473.864 | E93: 18388.27 | F93: 1040737.6
B94: 78 | C94: 29862.134 | D94: 11274.658 | E94: 18587.476 | F94: 1022150.2 | J94: =SUM(D83:D94) -> 147984.95 | K94: 12114
B95: 79 | C95: 29862.134 | D95: 11073.293 | E95: 18788.841 | F95: 1003361.3
B96: 80 | C96: 29862.134 | D96: 10869.748 | E96: 18992.387 | F96: 984368.94
B97: 81 | C97: 29862.134 | D97: 10663.997 | E97: 19198.137 | F97: 965170.8
B98: 82 | C98: 29862.134 | D98: 10456.017 | E98: 19406.117 | F98: 945764.68
B99: 83 | C99: 29862.134 | D99: 10245.784 | E99: 19616.35 | F99: 926148.33
B100: 84 | C100: 29862.134 | D100: 10033.274 | E100: 19828.861 | F100: 906319.47 | G100: 7 | I100: =SUM(D89:D100) -> 133935.8
B101: 85 | C101: 29862.134 | D101: 9818.4609 | E101: 20043.673 | F101: 886275.8
B102: 86 | C102: 29862.134 | D102: 9601.3211 | E102: 20260.813 | F102: 866014.98
B103: 87 | C103: 29862.134 | D103: 9381.829 | E103: 20480.305 | F103: 845534.68
B104: 88 | C104: 29862.134 | D104: 9159.959 | E104: 20702.175 | F104: 824832.5
B105: 89 | C105: 29862.134 | D105: 8935.6855 | E105: 20926.449 | F105: 803906.06
B106: 90 | C106: 29862.134 | D106: 8708.9823 | E106: 21153.152 | F106: 782752.9 | J106: =SUM(D95:D106) -> 118948.35 | K106: 12479
B107: 91 | C107: 29862.134 | D107: 8479.8231 | E107: 21382.311 | F107: 761370.59
...

Sheet OD
B5: M/S SHREE ENTERPRISES
B10: Year | C10: Opening OD Balance | D10: Principal Repayment | E10: Interest
B11: 2026-27 | C11: 3323350 | D11: 275350 | E11: =C11*9.5% -> 315718.25
B12: 2027-28 | C12: =C11-D11 -> 3048000 | D12: 291457 | E12: =C12*9.5% -> 289560
B13: 2028-29 | C13: =C12-D12 -> 2756543 | D13: 310750 | E13: =C13*9.5% -> 261871.58
B14: 2029-30 | C14: =C13-D13 -> 2445793 | D14: 340350 | E14: =C14*9.5% -> 232350.33
B15: 2030-31 | C15: =C14-D15 -> 2085043 | D15: 360750 | E15: =C15*9.5% -> 198079.08
B16: 2031-32 | C16: =C15-D15 -> 1724293 | D16: 380750 | E16: =C16*9.5% -> 163807.83
B17: 2032-33 | C17: =C16-D16 -> 1343543 | D17: 400150 | E17: =C17*9.5% -> 127636.59
B18: 2033-34 | C18: =C17-D17 -> 943393 | D18: 425750 | E18: =C18*9.5% -> 89622.335
B19: 2034-35 | C19: =C18-D18 -> 517643 | D19: 448750 | E19: =C19*9.5% -> 49176.085
B20: 2035-36 | C20: =D19 -> 448750 | D20: =C11-SUM(D11:D19) -> 89293 | E20: =C20*9.5% -> 42631.25
C21: =SUM(C11:C20) -> 18636351 | D21: =SUM(D11:D20) -> 3323350 | E21: =SUM(E11:E20) -> 1770453.3

Sheet Sheet1
B2: EMI CALCULATOR | I2: INSTRUCTION
B4: LOAN AMOUNT | D4: 765304 | F4: FILL UP | I4: Please Fill Up Only Loan Amount, Rate Per Annum,and Nos. of Installments it will Automatically shows you the details of EMIs
B6: RATE OF INTEREST PER ANNUM | D6: 0.13 | F6: FILL UP
B8: RATE OF INTEREST PER MONTH | D8: =D6/12 -> 0.010833333
B10: NO OF INSTALLMENT | D10: 24 | F10: FILL UP
D11: 62
B12: EMI | D12: =-PMT(D8,D10,D4) -> 36383.947
B14: CALCULATION OF DETAILS OF EMI
B16: MONTHS | C16: EMI | D16: INTEREST | E16: PRINCIPAL REPAYMENT | F16: OST PRINCIPAL
B17: 0 | F17: =D4 -> 765304
B18: 1 | C18: =D12 -> 36383.947 | D18: =F17*D8 -> 8290.7933 | E18: =C18-D18 -> 28093.154 | F18: =F17-E18 -> 737210.85
B19: 2 | C19: =D12 -> 36383.947 | D19: =F18*D8 -> 7986.4508 | E19: =C19-D19 -> 28397.496 | F19: =F18-E19 -> 708813.35
B20: 3 | C20: =D12 -> 36383.947 | D20: =F19*D8 -> 7678.8113 | E20: =C20-D20 -> 28705.136 | F20: =F19-E20 -> 680108.21 | G20: 44986 | I20: =SUM(D18:D20) -> 23956.055
B21: 4 | C21: =D12 -> 36383.947 | D21: =F20*D8 -> 7367.839 | E21: =C21-D21 -> 29016.108 | F21: =F20-E21 -> 651092.11
B22: 5 | C22: =D12 -> 36383.947 | D22: =F21*D8 -> 7053.4978 | E22: =C22-D22 -> 29330.449 | F22: =F21-E22 -> 621761.66
B23: 6 | C23: =D12 -> 36383.947 | D23: =F22*D8 -> 6735.7513 | E23: =C23-D23 -> 29648.196 | F23: =F22-E23 -> 592113.46
B24: 7 | C24: =D12 -> 36383.947 | D24: =F23*D8 -> 6414.5625 | E24: =C24-D24 -> 29969.384 | F24: =F23-E24 -> 562144.08
B25: 8 | C25: =D12 -> 36383.947 | D25: =F24*D8 -> 6089.8942 | E25: =C25-D25 -> 30294.053 | F25: =F24-E25 -> 531850.02
B26: 9 | C26: =D12 -> 36383.947 | D26: =F25*D8 -> 5761.7086 | E26: =C26-D26 -> 30622.238 | F26: =F25-E26 -> 501227.79
B27: 10 | C27: =D12 -> 36383.947 | D27: =F26*D8 -> 5429.9677 | E27: =C27-D27 -> 30953.979 | F27: =F26-E27 -> 470273.81
B28: 11 | C28: =D12 -> 36383.947 | D28: =F27*D8 -> 5094.6329 | E28: =C28-D28 -> 31289.314 | F28: =F27-E28 -> 438984.49
B29: 12 | C29: =D12 -> 36383.947 | D29: =F28*D8 -> 4755.6653 | E29: =C29-D29 -> 31628.282 | F29: =F28-E29 -> 407356.21
B30: 13 | C30: =D12 -> 36383.947 | D30: =F29*D8 -> 4413.0256 | E30: =C30-D30 -> 31970.921 | F30: =F29-E30 -> 375385.29
B31: 14 | C31: =D12 -> 36383.947 | D31: =F30*D8 -> 4066.674 | E31: =C31-D31 -> 32317.273 | F31: =F30-E31 -> 343068.02
B32: 15 | C32: =D12 -> 36383.947 | D32: =F31*D8 -> 3716.5702 | E32: =C32-D32 -> 32667.377 | F32: =F31-E32 -> 310400.64 | G32: 45352 | I32: =SUM(D21:D32) -> 66899.789
B33: 16 | C33: =D12 -> 36383.947 | D33: =F32*D8 -> 3362.6736 | E33: =C33-D33 -> 33021.273 | F33: =F32-E33 -> 277379.37
B34: 17 | C34: =D12 -> 36383.947 | D34: =F33*D8 -> 3004.9431 | E34: =C34-D34 -> 33379.004 | F34: =F33-E34 -> 244000.36
B35: 18 | C35: =D12 -> 36383.947 | D35: =F34*D8 -> 2643.3373 | E35: =C35-D35 -> 33740.61 | F35: =F34-E35 -> 210259.75
B36: 19 | C36: =D12 -> 36383.947 | D36: =F35*D8 -> 2277.814 | E36: =C36-D36 -> 34106.133 | F36: =F35-E36 -> 176153.62
B37: 20 | C37: =D12 -> 36383.947 | D37: =F36*D8 -> 1908.3309 | E37: =C37-D37 -> 34475.616 | F37: =F36-E37 -> 141678
B38: 21 | C38: =D12 -> 36383.947 | D38: =F37*D8 -> 1534.845 | E38: =C38-D38 -> 34849.102 | F38: =F37-E38 -> 106828.9
B39: 22 | C39: =D12 -> 36383.947 | D39: =F38*D8 -> 1157.3131 | E39: =C39-D39 -> 35226.634 | F39: =F38-E39 -> 71602.268
B40: 23 | C40: =D12 -> 36383.947 | D40: =F39*D8 -> 775.69123 | E40: =C40-D40 -> 35608.256 | F40: =F39-E40 -> 35994.012
B41: 24 | C41: =D12 -> 36383.947 | D41: =F40*D8 -> 389.93513 | E41: =C41-D41 -> 35994.012 | F41: =F40-E41 -> 1.3824319e-10
B42: 25 | C42: =D12 -> 36383.947 | D42: =F41*D8 -> 1.4976346e-12 | E42: =C42-D42 -> 36383.947 | F42: =F41-E42 -> -36383.947
B43: 26 | C43: =D12 -> 36383.947 | D43: =F42*D8 -> -394.15943 | E43: =C43-D43 -> 36778.106 | F43: =F42-E43 -> -73162.053
B44: 27 | C44: =D12 -> 36383.947 | D44: =F43*D8 -> -792.58891 | E44: =C44-D44 -> 37176.536 | F44: =F43-E44 -> -110338.59 | G44: 45717 | I44: =SUM(D33:D44) -> 15868.135
B45: 28 | C45: =D12 -> 36383.947 | D45: =F44*D8 -> -1195.3347 | E45: =C45-D45 -> 37579.282 | F45: =F44-E45 -> -147917.87
B46: 29 | C46: =D12 -> 36383.947 | D46: =F45*D8 -> -1602.4436 | E46: =C46-D46 -> 37986.391 | F46: =F45-E46 -> -185904.26
B47: 30 | C47: =D12 -> 36383.947 | D47: =F46*D8 -> -2013.9628 | E47: =C47-D47 -> 38397.91 | F47: =F46-E47 -> -224302.17
B48: 31 | C48: =D12 -> 36383.947 | D48: =F47*D8 -> -2429.9402 | E48: =C48-D48 -> 38813.887 | F48: =F47-E48 -> -263116.06
B49: 32 | C49: =D12 -> 36383.947 | D49: =F48*D8 -> -2850.424 | E49: =C49-D49 -> 39234.371 | F49: =F48-E49 -> -302350.43
B50: 33 | C50: =D12 -> 36383.947 | D50: =F49*D8 -> -3275.463 | E50: =C50-D50 -> 39659.41 | F50: =F49-E50 -> -342009.84
B51: 34 | C51: =D12 -> 36383.947 | D51: =F50*D8 -> -3705.1066 | E51: =C51-D51 -> 40089.054 | F51: =F50-E51 -> -382098.89
B52: 35 | C52: =D12 -> 36383.947 | D52: =F51*D8 -> -4139.4047 | E52: =C52-D52 -> 40523.352 | F52: =F51-E52 -> -422622.24
B53: 36 | C53: =D12 -> 36383.947 | D53: =F52*D8 -> -4578.4077 | E53: =C53-D53 -> 40962.355 | F53: =F52-E53 -> -463584.6
B54: 37 | C54: =D12 -> 36383.947 | D54: =F53*D8 -> -5022.1665 | E54: =C54-D54 -> 41406.113 | F54: =F53-E54 -> -504990.71
B55: 38 | C55: =$D$12 -> 36383.947 | D55: =F54*D8 -> -5470.7327 | E55: =C55-D55 -> 41854.68 | F55: =F54-E55 -> -546845.39
B56: 39 | C56: =$D$12 -> 36383.947 | D56: =F55*D8 -> -5924.1584 | E56: =C56-D56 -> 42308.105 | F56: =F55-E56 -> -589153.5 | G56: 46082 | I56: =SUM(D45:D56) -> -42207.545
B57: 40 | C57: =$D$12 -> 36383.947 | D57: =F56*D8 -> -6382.4962 | E57: =C57-D57 -> 42766.443 | F57: =F56-E57 -> -631919.94
B58: 41 | C58: =$D$12 -> 36383.947 | D58: =F57*D8 -> -6845.7994 | E58: =C58-D58 -> 43229.746 | F58: =F57-E58 -> -675149.69
B59: 42 | C59: =$D$12 -> 36383.947 | D59: =F58*D8 -> -7314.1216 | E59: =C59-D59 -> 43698.069 | F59: =F58-E59 -> -718847.76
B60: 43 | C60: =$D$12 -> 36383.947 | D60: =F59*D8 -> -7787.5174 | E60: =C60-D60 -> 44171.464 | F60: =F59-E60 -> -763019.22
B61: 44 | C61: =$D$12 -> 36383.947 | D61: =F60*D8 -> -8266.0416 | E61: =C61-D61 -> 44649.989 | F61: =F60-E61 -> -807669.21
B62: 45 | C62: =$D$12 -> 36383.947 | D62: =F61*D8 -> -8749.7498 | E62: =C62-D62 -> 45133.697 | F62: =F61-E62 -> -852802.91
B63: 46 | C63: =$D$12 -> 36383.947 | D63: =F62*D8 -> -9238.6981 | E63: =C63-D63 -> 45622.645 | F63: =F62-E63 -> -898425.55
B64: 47 | C64: =$D$12 -> 36383.947 | D64: =F63*D8 -> -9732.9435 | E64: =C64-D64 -> 46116.89 | F64: =F63-E64 -> -944542.44
B65: 48 | C65: =$D$12 -> 36383.947 | D65: =F64*D8 -> -10232.543 | E65: =C65-D65 -> 46616.49 | F65: =F64-E65 -> -991158.93
B66: 49 | C66: =$D$12 -> 36383.947 | D66: =F65*D8 -> -10737.555 | E66: =C66-D66 -> 47121.502 | F66: =F65-E66 -> -1038280.4
B67: 50 | C67: =$D$12 -> 36383.947 | D67: =F66*D8 -> -11248.038 | E67: =C67-D67 -> 47631.985 | F67: =F66-E67 -> -1085912.4
B68: 51 | C68: =$D$12 -> 36383.947 | D68: =F67*D8 -> -11764.051 | E68: =C68-D68 -> 48147.998 | F68: =F67-E68 -> -1134060.4 | G68: 46447 | I68: =SUM(D57:D68) -> -108299.55
B69: 52 | C69: =$D$12 -> 36383.947 | D69: =F68*D8 -> -12285.655 | E69: =C69-D69 -> 48669.602 | F69: =F68-E69 -> -1182730
B70: 53 | C70: =$D$12 -> 36383.947 | D70: =F69*D8 -> -12812.909 | E70: =C70-D70 -> 49196.856 | F70: =F69-E70 -> -1231926.9
B71: 54 | C71: =$D$12 -> 36383.947 | D71: =F70*D8 -> -13345.874 | E71: =C71-D71 -> 49729.821 | F71: =F70-E71 -> -1281656.7
B72: 55 | C72: =$D$12 -> 36383.947 | D72: =F71*D8 -> -13884.614 | E72: =C72-D72 -> 50268.561 | F72: =F71-E72 -> -1331925.3
B73: 56 | C73: =$D$12 -> 36383.947 | D73: =F72*D8 -> -14429.19 | E73: =C73-D73 -> 50813.137 | F73: =F72-E73 -> -1382738.4
B74: 57 | C74: =$D$12 -> 36383.947 | D74: =F73*D8 -> -14979.666 | E74: =C74-D74 -> 51363.613 | F74: =F73-E74 -> -1434102
B75: 58 | C75: =$D$12 -> 36383.947 | D75: =F74*D8 -> -15536.105 | E75: =C75-D75 -> 51920.052 | F75: =F74-E75 -> -1486022.1
B76: 59 | C76: =$D$12 -> 36383.947 | D76: =F75*D8 -> -16098.572 | E76: =C76-D76 -> 52482.519 | F76: =F75-E76 -> -1538504.6
B77: 60 | C77: =$D$12 -> 36383.947 | D77: =F76*D8 -> -16667.133 | E77: =C77-D77 -> 53051.08 | F77: =F76-E77 -> -1591555.7 | G77: 46813 | I77: =SUM(D69:D77) -> -130039.72
B78: 61 | C78: =$D$12 -> 36383.947
B79: 62 | C79: =$D$12 -> 36383.947
B80: 63 | C80: =$D$12 -> 36383.947
B81: 64 | C81: =$D$12 -> 36383.947
B82: 65 | C82: =$D$12 -> 36383.947
B83: 66 | C83: =$D$12 -> 36383.947
B84: 67 | C84: =$D$12 -> 36383.947
B85: 68 | C85: =$D$12 -> 36383.947
B86: 69 | C86: =$D$12 -> 36383.947
B87: 70 | C87: =$D$12 -> 36383.947
B88: 71 | C88: =$D$12 -> 36383.947
B89: 72 | C89: =$D$12 -> 36383.947
... B101: 84 | C101: =$D$12 -> 36383.947
B124: Present Value Annuity Factor Table
B126: 100 | C126: =100+100*D8 -> 101.08333 | D126: =B126/C126 -> 0.98928277
B127: 100 | C127: =C126+C126*D8 -> 102.1784 | D127: =B127/C127 -> 0.9786804
B128: 100 | C128: =C127+C127*D8 -> 103.28534 | D128: =B128/C128 -> 0.96819166
B129: 100 | C129: =C128+C128*D8 -> 104.40426 | D129: =B129/C129 -> 0.95781532
B130: 100 | C130: =C129+C129*D8 -> 105.53531 | D130: =B130/C130 -> 0.9475502
B131: 100 | C131: =C130+C130*D8 -> 106.67861 | D131: =B131/C131 -> 0.93739508
B132: 100 | C132: =C131+C131*D8 -> 107.83429 | D132: =B132/C132 -> 0.9273488
B133: 100 | C133: =C132+C132*D8 -> 109.00249 | D133: =B133/C133 -> 0.91741019
B134: 100 | C134: =C133+C133*D8 -> 110.18336 | D134: =B134/C134 -> 0.9075781
B135: 100 | C135: =C134+C134*D8 -> 111.37701 | D135: =B135/C135 -> 0.89785137
B136: 100 | C136: =C135+C135*D8 -> 112.58359 | D136: =B136/C136 -> 0.88822889
B137: 100 | C137: =C136+C136*D8 -> 113.80325 | D137: =B137/C137 -> 0.87870954
B138: 100 | C138: =C137+C137*D8 -> 115.03612 | D138: =B138/C138 -> 0.86929221
B139: 100 | C139: =C138+C138*D8 -> 116.28234 | D139: =B139/C139 -> 0.8599758
B140: 100 | C140: =C139+C139*D8 -> 117.54207 | D140: =B140/C140 -> 0.85075925
B141: 100 | C141: =C140+C140*D8 -> 118.81544 | D141: =B141/C141 -> 0.84164146
...
